unrealcli/__init__.py
unreal_cli-0.0.0.dist-info/METADATA
unreal_cli-0.0.0.dist-info/WHEEL
unreal_cli-0.0.0.dist-info/top_level.txt
unreal_cli-0.0.0.dist-info/zip-safe
unreal_cli-0.0.0.dist-info/RECORD
